sandlercubics/__init__.py
sandlercubics/cli.py
sandlercubics/eos.py
sandlercubics-0.2.0.dist-info/METADATA
sandlercubics-0.2.0.dist-info/WHEEL
sandlercubics-0.2.0.dist-info/entry_points.txt
sandlercubics-0.2.0.dist-info/licenses/LICENSE
sandlercubics-0.2.0.dist-info/RECORD
