Metadata-Version: 2.4
Name: sandlercubics
Version: 0.2.0
Summary: Cubic equations of state from Chemical, Biochemical, and Engineering Thermodynamics (5th edition) by Stan Sandler
Author-email: Cameron F Abrams <cfa22@drexel.edu>
License-File: LICENSE
Classifier: License :: OSI Approved :: MIT License
Classifier: Programming Language :: Python :: 3
Requires-Python: >=3.7
Requires-Dist: numpy
Requires-Dist: scipy
